README.md
config.example.json
config.plugin_example.py
setup.py
bin/pandora_client
debian/changelog
debian/compat
debian/control
debian/copyright
debian/rules
debian/source/format
pandora_client/__init__.py
pandora_client/client.py
pandora_client/extract.py
pandora_client/localnode.py
pandora_client/server.py
pandora_client/utils.py
pandora_client.egg-info/PKG-INFO
pandora_client.egg-info/SOURCES.txt
pandora_client.egg-info/dependency_links.txt
pandora_client.egg-info/pbr.json
pandora_client.egg-info/requires.txt
pandora_client.egg-info/top_level.txt