Metadata-Version: 2.1
Name: pandora-client
Version: 0.3.24
Summary: pandora_client is a commandline client for pan.do/ra. You can use it to import videos into a pan.do/ra system. It is currently known to work on Linux and Mac OS X.
Home-page: https://code.0x2620.org/0x2620/pandora_client/wiki
Author: j
Author-email: j@mailb.org
License: GPLv3
Classifier: Development Status :: 5 - Production/Stable
Classifier: Environment :: Console
Classifier: Operating System :: OS Independent
Classifier: Programming Language :: Python :: 3
Classifier: License :: OSI Approved :: GNU General Public License (GPL)
